poetry_aliases_plugin/__init__.py
poetry_aliases_plugin/__main__.py
poetry_aliases_plugin/aliases.py
poetry_aliases_plugin/config.py
poetry_aliases_plugin/plugin.py
poetry_aliases_plugin/plugin_commands.py
poetry_aliases_plugin/triggers.py
poetry_aliases_plugin/utils.py
poetry_aliases_plugin-0.1.1.dist-info/entry_points.txt
poetry_aliases_plugin-0.1.1.dist-info/LICENSE
poetry_aliases_plugin-0.1.1.dist-info/WHEEL
poetry_aliases_plugin-0.1.1.dist-info/METADATA
poetry_aliases_plugin-0.1.1.dist-info/RECORD
