Metadata-Version: 2.1
Name: poetry-aliases-plugin
Version: 0.1.1
Summary: Poetry plugin to run commands through aliases
Home-page: https://github.com/rocshers/poetry-alias-plugin
License: MIT
Author: irocshers
Author-email: develop.iam@rocshers.com
Requires-Python: >=3.10
Classifier: Intended Audience :: Developers
Classifier: License :: OSI Approved :: MIT License
Classifier: Programming Language :: Python :: 3
Classifier: Programming Language :: Python :: 3.10
Classifier: Programming Language :: Python :: 3.11
Classifier: Topic :: Software Development :: Build Tools
Requires-Dist: poetry (>=1.2.0)
Project-URL: Repository, https://github.com/rocshers/poetry-alias-plugin
